must/__init__.py
must/__main__.py
must-0.1.0.dist-info/WHEEL
must-0.1.0.dist-info/METADATA
must-0.1.0.dist-info/RECORD
