Metadata-Version: 2.1
Name: must
Version: 0.1.0
Summary: Multi-Stage Programming for Python
Keywords: must
Requires-Python: >=3.7
Classifier: Topic :: Software Development
Classifier: Programming Language :: Python :: 3
Requires-Dist: libcst
